{"run_number": "1775528943237195", "step_name": "spark_features", "task_id": "6", "attempt_id": 0, "name": "num_leaves", "content_type": "gzip+pickle-v4", "type": "metaflow.artifact", "sha": "6fe7bad759617f420873738a222e7dcce7381515", "ds_type": "local", "location": ":root:/Users/akilalourdes/streaming-canvas-search-ltr/.metaflow", "flow_id": "StreamLensFlow", "user_name": "akilalourdes", "tags": [], "system_tags": ["user:akilalourdes", "python_version:3.12.12", "metaflow_version:2.19.22", "runtime:dev"], "ts_epoch": 1775528974599}