{"run_number": "1770707144330957", "step_name": "start", "task_id": "1", "attempt_id": 0, "name": "api_port", "content_type": "gzip+pickle-v4", "type": "metaflow.artifact", "sha": "eb5a377eea1aacbf6ca3f078075bd6b4a2b35849", "ds_type": "local", "location": ":root:/Users/akilalourdes/streaming-canvas-search-ltr/.metaflow", "flow_id": "StreamingSearchLTRFlow", "user_name": "akilalourdes", "tags": [], "system_tags": ["runtime:dev", "python_version:3.11.14", "metaflow_version:2.19.19", "user:akilalourdes"], "ts_epoch": 1770707144464}