{"run_number": "1770707137285567", "step_name": "train_ltr", "task_id": "5", "attempt_id": 0, "name": "name", "content_type": "gzip+pickle-v4", "type": "metaflow.artifact", "sha": "746d178f568e6d0f944470f3b960e574cb8119dd", "ds_type": "local", "location": ":root:/Users/akilalourdes/streaming-canvas-search-ltr/.metaflow", "flow_id": "StreamingSearchLTRFlow", "user_name": "akilalourdes", "tags": [], "system_tags": ["metaflow_version:2.19.19", "runtime:dev", "user:akilalourdes", "python_version:3.11.14"], "ts_epoch": 1770707137309}